invenio_communities/__init__.py
invenio_communities/cli.py
invenio_communities/config.py
invenio_communities/errors.py
invenio_communities/ext.py
invenio_communities/generators.py
invenio_communities/permissions.py
invenio_communities/proxies.py
invenio_communities/roles.py
invenio_communities/searchapp.py
invenio_communities/tasks.py
invenio_communities/utils.py
invenio_communities/webpack.py
invenio_communities/administration/__init__.py
invenio_communities/administration/communities.py
invenio_communities/alembic/02cd82910727_update_role_id_type_upgrade.py
invenio_communities/alembic/37b21951084c_update_role_id_type_downgrade.py
invenio_communities/alembic/5b478fe7ef7f_create_featured_communities_table.py
invenio_communities/alembic/5c68d45c80f0_add_deletion_status_to_communities.py
invenio_communities/alembic/72b37bb4119c_create_indeces_for_bucket_id.py
invenio_communities/alembic/90642d415317_create_communities_branch.py
invenio_communities/alembic/__init__.py
invenio_communities/alembic/a3f5a8635cbb_remove_version_table.py
invenio_communities/alembic/de9c14cbb0b2_create_communities_tables.py
invenio_communities/alembic/f701a32e6fbe_create_communities_members_table.py
invenio_communities/alembic/fbe746957cfc_create_member_tables.py
invenio_communities/assets/semantic-ui/js/invenio_communities/administration/FeatureModal.js
invenio_communities/assets/semantic-ui/js/invenio_communities/administration/details.js
invenio_communities/assets/semantic-ui/js/invenio_communities/administration/featured.js
invenio_communities/assets/semantic-ui/js/invenio_communities/administration/search.js
invenio_communities/assets/semantic-ui/js/invenio_communities/administration/api/api.js
invenio_communities/assets/semantic-ui/js/invenio_communities/administration/api/index.js
invenio_communities/assets/semantic-ui/js/invenio_communities/administration/api/routes.js
invenio_communities/assets/semantic-ui/js/invenio_communities/administration/components/RecordResourceActions.js
invenio_communities-22.0.0.dist-info/licenses/AUTHORS.rst
invenio_communities-22.0.0.dist-info/licenses/LICENSE
invenio_communities-22.0.0.dist-info/METADATA
invenio_communities-22.0.0.dist-info/WHEEL
invenio_communities-22.0.0.dist-info/entry_points.txt
invenio_communities-22.0.0.dist-info/top_level.txt
invenio_communities-22.0.0.dist-info/RECORD
