Metadata-Version: 2.4
Name: invenio-communities
Version: 22.0.0
Summary: InvenioRDM module for the communities feature.
Home-page: https://github.com/inveniosoftware/invenio-communities
Author: CERN
Author-email: info@inveniosoftware.org
License: MIT
Keywords: invenio communities
Platform: any
Classifier: Development Status :: 5 - Production/Stable
Requires-Python: >=3.8
License-File: LICENSE
License-File: AUTHORS.rst
Requires-Dist: invenio-oaiserver<4.0.0,>=3.0.0
Requires-Dist: invenio-records-resources<9.0.0,>=8.0.0
Requires-Dist: invenio-requests<12.0.0,>=11.0.0
Requires-Dist: invenio-search-ui<5.0.0,>=4.0.0
Requires-Dist: invenio-vocabularies<10.0.0,>=9.0.0
Requires-Dist: invenio-administration<5.0.0,>=4.0.0
Provides-Extra: tests
Requires-Dist: pytest-black-ng>=0.4.0; extra == "tests"
Requires-Dist: Faker>=2.0.3; extra == "tests"
Requires-Dist: invenio-app<3.0.0,>=2.1.0; extra == "tests"
Requires-Dist: invenio-db[mysql,postgresql]<3.0.0,>=2.0.0; extra == "tests"
Requires-Dist: pytest-invenio<4.0.0,>=3.0.0; extra == "tests"
Requires-Dist: sphinx>=4.5.0; extra == "tests"
Provides-Extra: opensearch1
Requires-Dist: invenio-search[opensearch1]<4.0.0,>=3.0.0; extra == "opensearch1"
Provides-Extra: opensearch2
Requires-Dist: invenio-search[opensearch2]<4.0.0,>=3.0.0; extra == "opensearch2"
Dynamic: license-file
